zbpp_light/__init__.py
zbpp_light/auto_schedule.py
zbpp_light/weight_grad_store.py
zbpp_light/zb_schedule.py
zbpp_light/zbpp_light.py
zbpp_light-0.0.1.dist-info/LICENSE
zbpp_light-0.0.1.dist-info/METADATA
zbpp_light-0.0.1.dist-info/WHEEL
zbpp_light-0.0.1.dist-info/top_level.txt
zbpp_light-0.0.1.dist-info/RECORD
