Metadata-Version: 2.1
Name: zbpp-light
Version: 0.0.1
Summary: Zero Bubble Pipeline Parallelism (ZBPP) light weight implementation. For more details refer to https://github.com/sail-sg/zero-bubble-pipeline-parallelism.
Home-page: https://github.com/sail-sg/zero-bubble-pipeline-parallelism
Author: Qi Penghui, Wan Xinyi, Huang Guangxing, Lin Min
Author-email: wanxy@sea.com
Requires-Python: >=3.8
License-File: LICENSE
